{
    "_id": "leviticus9",
    "nextChapterId": "leviticus10",
    "prevChapterId": "leviticus8",
    "volume": {
        "title": "Old Testament",
        "titleShort": "OT",
        "titleOfficial": "The Old Testament",
        "_id": "oldtestament"
    },
    "book": {
        "title": "Leviticus",
        "titleShort": "Lev",
        "titleOfficial": "",
        "subtitle": "",
        "summary": "",
        "_id": "leviticus"
    },
    "chapter": {
        "bookTitle": "Leviticus",
        "delineation": "Chapter",
        "number": 9,
        "summary": "Aaron makes an atonement by sacrifice for himself and all Israel\u2014He and his sons offer sacrifices\u2014The glory of the Lord appears to all\u2014Fire from the Lord consumes the offerings on the altar.",
        "chapterAugmentations": [],
        "verses": [
            {
                "text": "And it came to pass on the eighth day, that Moses called Aaron and his sons, and the elders of Israel;",
                "footnotes": [
                    {
                        "footnote": "Ezek. 43:27.",
                        "start": 27,
                        "end": 33
                    },
                    {
                        "footnote": "Alma 6:1; D&C 46:2.",
                        "start": 85,
                        "end": 91
                    }
                ],
                "associatedContents": [],
                "italics": [
                    {
                        "start": 39,
                        "end": 43
                    }
                ]
            },
            {
                "text": "And he said unto Aaron, Take thee a young calf for a sin offering, and a ram for a burnt offering, without blemish, and offer them before the Lord.",
                "footnotes": [],
                "associatedContents": [],
                "italics": [
                    {
                        "start": 126,
                        "end": 130
                    }
                ]
            },
            {
                "text": "And unto the children of Israel thou shalt speak, saying, Take ye a kid of the goats for a sin offering; and a calf and a lamb, both of the first year, without blemish, for a burnt offering;",
                "footnotes": [
                    {
                        "footnote": "Lev. 10:16 (16\u201319).",
                        "start": 79,
                        "end": 84
                    }
                ],
                "associatedContents": [],
                "italics": [
                    {
                        "start": 128,
                        "end": 132
                    }
                ]
            },
            {
                "text": "Also a bullock and a ram for peace offerings, to sacrifice before the Lord; and a meat offering mingled with oil: for to day the Lord will appear unto you.",
                "footnotes": [
                    {
                        "footnote": "D&C 67:10 (10\u201312); 88:68; 93:1.",
                        "start": 139,
                        "end": 145
                    }
                ],
                "associatedContents": [],
                "italics": []
            },
            {
                "text": "And they brought that which Moses commanded before the tabernacle of the congregation: and all the congregation drew near and stood before the Lord.",
                "footnotes": [
                    {
                        "footnote": "TG\u00a0God, Access to.",
                        "start": 117,
                        "end": 121
                    }
                ],
                "associatedContents": [],
                "italics": [
                    {
                        "start": 17,
                        "end": 21
                    }
                ]
            },
            {
                "text": "And Moses said, This is the thing which the Lord commanded that ye should do: and the glory of the Lord shall appear unto you.",
                "footnotes": [
                    {
                        "footnote": "Lev. 9:23; 2\u00a0Ne. 1:15; Ether 12:6 (6\u201318).",
                        "start": 86,
                        "end": 91
                    }
                ],
                "associatedContents": [],
                "italics": [
                    {
                        "start": 21,
                        "end": 23
                    }
                ]
            },
            {
                "text": "And Moses said unto Aaron, Go unto the altar, and offer thy sin offering, and thy burnt offering, and make an atonement for thyself, and for the people: and offer the offering of the people, and make an atonement for them; as the Lord commanded.",
                "footnotes": [],
                "associatedContents": [],
                "italics": []
            },
            {
                "text": "Aaron therefore went unto the altar, and slew the calf of the sin offering, which was for himself.",
                "footnotes": [],
                "associatedContents": [],
                "italics": [
                    {
                        "start": 82,
                        "end": 85
                    }
                ]
            },
            {
                "text": "And the sons of Aaron brought the blood unto him: and he dipped his finger in the blood, and put it upon the horns of the altar, and poured out the blood at the bottom of the altar:",
                "footnotes": [
                    {
                        "footnote": "Lev. 4:7.",
                        "start": 109,
                        "end": 114
                    }
                ],
                "associatedContents": [],
                "italics": [
                    {
                        "start": 97,
                        "end": 99
                    }
                ]
            },
            {
                "text": "But the fat, and the kidneys, and the caul above the liver of the sin offering, he burnt upon the altar; as the Lord commanded Moses.",
                "footnotes": [],
                "associatedContents": [],
                "italics": []
            },
            {
                "text": "And the flesh and the hide he burnt with fire without the camp.",
                "footnotes": [],
                "associatedContents": [],
                "italics": []
            },
            {
                "text": "And he slew the burnt offering; and Aaron's sons presented unto him the blood, which he sprinkled round about upon the altar.",
                "footnotes": [],
                "associatedContents": [],
                "italics": []
            },
            {
                "text": "And they presented the burnt offering unto him, with the pieces thereof, and the head: and he burnt them upon the altar.",
                "footnotes": [],
                "associatedContents": [],
                "italics": [
                    {
                        "start": 100,
                        "end": 104
                    }
                ]
            },
            {
                "text": "And he did wash the inwards and the legs, and burnt them upon the burnt offering on the altar.",
                "footnotes": [],
                "associatedContents": [
                    {
                        "type": "paper-page-number",
                        "data": 158
                    }
                ],
                "italics": [
                    {
                        "start": 52,
                        "end": 56
                    }
                ]
            },
            {
                "text": "And he brought the people's offering, and took the goat, which was the sin offering for the people, and slew it, and offered it for sin, as the first.",
                "footnotes": [
                    {
                        "footnote": "Judg. 13:19 (19\u201320).",
                        "start": 75,
                        "end": 83
                    }
                ],
                "associatedContents": [],
                "italics": [
                    {
                        "start": 63,
                        "end": 66
                    }
                ]
            },
            {
                "text": "And he brought the burnt offering, and offered it according to the manner.",
                "footnotes": [
                    {
                        "footnote": "HEB\u00a0statute.",
                        "start": 67,
                        "end": 73
                    }
                ],
                "associatedContents": [],
                "italics": []
            },
            {
                "text": "And he brought the meat offering, and took an handful thereof, and burnt it upon the altar, beside the burnt sacrifice of the morning.",
                "footnotes": [],
                "associatedContents": [],
                "italics": [
                    {
                        "start": 73,
                        "end": 75
                    }
                ]
            },
            {
                "text": "He slew also the bullock and the ram for a sacrifice of peace offerings, which was for the people: and Aaron's sons presented unto him the blood, which he sprinkled upon the altar round about,",
                "footnotes": [],
                "associatedContents": [],
                "italics": [
                    {
                        "start": 37,
                        "end": 40
                    },
                    {
                        "start": 79,
                        "end": 82
                    }
                ]
            },
            {
                "text": "And the fat of the bullock and of the ram, the rump, and that which covereth the inwards, and the kidneys, and the caul above the liver:",
                "footnotes": [],
                "associatedContents": [],
                "italics": [
                    {
                        "start": 77,
                        "end": 89
                    },
                    {
                        "start": 120,
                        "end": 125
                    }
                ]
            },
            {
                "text": "And they put the fat upon the breasts, and he burnt the fat upon the altar:",
                "footnotes": [],
                "associatedContents": [],
                "italics": []
            },
            {
                "text": "And the breasts and the right shoulder Aaron waved for a wave offering before the Lord; as Moses commanded.",
                "footnotes": [],
                "associatedContents": [],
                "italics": [
                    {
                        "start": 51,
                        "end": 54
                    }
                ]
            },
            {
                "text": "And Aaron lifted up his hand toward the people, and blessed them, and came down from offering of the sin offering, and the burnt offering, and peace offerings.",
                "footnotes": [],
                "associatedContents": [],
                "italics": []
            },
            {
                "text": "And Moses and Aaron went into the tabernacle of the congregation, and came out, and blessed the people: and the glory of the Lord appeared unto all the people.",
                "footnotes": [
                    {
                        "footnote": "Lev. 9:6; 2\u00a0Ne. 1:15; Ether 12:6 (6\u201318).",
                        "start": 112,
                        "end": 117
                    }
                ],
                "associatedContents": [],
                "italics": []
            },
            {
                "text": "And there came a fire out from before the Lord, and consumed upon the altar the burnt offering and the fat: which when all the people saw, they shouted, and fell on their faces.",
                "footnotes": [
                    {
                        "footnote": "Lev. 10:2; Judg. 6:21; 1\u00a0Chr. 21:26; 2\u00a0Chr. 7:1; 1\u00a0Ne. 1:6.",
                        "start": 17,
                        "end": 21
                    }
                ],
                "associatedContents": [],
                "italics": [
                    {
                        "start": 108,
                        "end": 113
                    }
                ]
            }
        ]
    }
}