{
    "_id": "jacob",
    "title": "Jacob",
    "titleShort": "Jacob",
    "titleOfficial": "",
    "subtitle": "",
    "summary": "",
    "chapterDelineation": "Chapter",
    "chapters": [
        {
            "_id": "jacob1",
            "summary": ""
        },
        {
            "_id": "jacob2",
            "summary": ""
        },
        {
            "_id": "jacob3",
            "summary": ""
        },
        {
            "_id": "jacob4",
            "summary": ""
        },
        {
            "_id": "jacob5",
            "summary": ""
        },
        {
            "_id": "jacob6",
            "summary": ""
        },
        {
            "_id": "jacob7",
            "summary": ""
        }
    ]
}